CHANGELOG.rst
LICENSE
MANIFEST.in
README.rst
helga_hipchat_nicks.py
requirements.txt
setup.py
helga_hipchat_nicks.egg-info/PKG-INFO
helga_hipchat_nicks.egg-info/SOURCES.txt
helga_hipchat_nicks.egg-info/dependency_links.txt
helga_hipchat_nicks.egg-info/entry_points.txt
helga_hipchat_nicks.egg-info/requires.txt
helga_hipchat_nicks.egg-info/top_level.txt
helga_hipchat_nicks.egg-info/zip-safe