Metadata-Version: 1.1
Name: helga-hipchat-nicks
Version: 0.1.1
Summary: A helga preprocessor to ensure that user nicks are set as @ mentions
Home-page: https://github.com/shaunduncan/helga-hipchat-nicks
Author: Shaun Duncan
Author-email: shaun.duncan@gmail.com
License: UNKNOWN
Keywords: helga hipchat
Platform: UNKNOWN
Classifier: Development Status :: 4 - Beta
Classifier: Topic :: Communications :: Chat :: Internet Relay Chat
Classifier: Framework :: Twisted
Classifier: License :: OSI Approved :: MIT License
Classifier: Operating System :: OS Independent
Classifier: Programming Language :: Python
Classifier: Programming Language :: Python :: 2
Classifier: Programming Language :: Python :: 2.6
Classifier: Programming Language :: Python :: 2.7
Classifier: Topic :: Software Development :: Libraries :: Python Modules
